MANIFEST.in
README.md
setup.py
emanual/_.py
emanual/__init__.py
emanual/cli.py
emanual/filename.py
emanual/make.py
emanual.egg-info/PKG-INFO
emanual.egg-info/SOURCES.txt
emanual.egg-info/dependency_links.txt
emanual.egg-info/entry_points.txt
emanual.egg-info/requires.txt
emanual.egg-info/top_level.txt