Metadata-Version: 1.1
Name: emanual
Version: 0.4.4
Summary: EManual CLI - Command Line Interface for EManual
Home-page: https://github.com/EManual/EManual-CLI
Author: Jayin Ton
Author-email: tonjayin@gmail.name
License: MIT
Keywords: emanual cli
Platform: UNKNOWN
Classifier: Development Status :: 5 - Production/Stable
Classifier: Programming Language :: Python
Classifier: Programming Language :: Python :: 2
Classifier: Programming Language :: Python :: 2.7
Classifier: Programming Language :: Python :: 3
Classifier: Programming Language :: Python :: 3.4
Classifier: Environment :: Console
Classifier: Intended Audience :: Developers
Classifier: Intended Audience :: System Administrators
Classifier: License :: OSI Approved :: MIT License
